payment/__init__.py
payment/admin.py
payment/apps.py
payment/models.py
payment/settings.py
payment/tests.py
payment/urls.py
payment/utils.py
payment/views.py
payment/email_sender/__init__.py
payment/email_sender/email_sender.py
payment/migrations/__init__.py
payment/static/css/payment.css
payment/templates/base_templates/base.html
payment/templates/email_sender/notify_admin.html
payment/templates/email_sender/payment_email.html
payment/templates/payment/payment.html
payment/templates/payment/payment_details.html
payment/templates/payment/success.html
django_payment_manager-1.0.1.dist-info/LICENSE
django_payment_manager-1.0.1.dist-info/METADATA
django_payment_manager-1.0.1.dist-info/WHEEL
django_payment_manager-1.0.1.dist-info/top_level.txt
django_payment_manager-1.0.1.dist-info/RECORD
